lab9/TLC.v
`timescale 1ns / 1ps

module TLC (clk, rstn, HS, FS, HR, HY, HG, HL, FR, FY, FL);
    // lights = HR, HY, HG, HL, FR, FY, FL
    input wire clk, rstn, HS, FS;
    output wire HR, HY, HG, HL, FR, FY, FL;
    
    reg [6:0] lights;
    reg [2:0] state;
    reg select;

    localparam S0 = 3'b000,
               S1 = 3'b001,
               S2 = 3'b010,
               S3 = 3'b011,
               S4 = 3'b100,
               S5 = 3'b101;

    assign HR = lights[6];
    assign HY = lights[5];
    assign HG = lights[4];
    assign HL = lights[3];
    assign FR = lights[2];
    assign FY = lights[1];
    assign FL = lights[0];

    always @(posedge clk or posedge rstn) begin
        if (rstn) begin
            state <= S0;
            select <= 1'b1;
        end

        else begin
            case (state)
                S0 : begin
                    if (!HS && FS) begin
                        select <= 1'b1;
                        state <= S1;
                    end
                    else if (HS) begin
                        select <= 1'b0;
                        state <= S1;
                    end
                    else state <= S0;
                end

                S1 : begin
                    if (select) begin
                        state <= S3;
                        select <= 1'b0;
                    end
                    else state <= S2;
                end

                S2 : begin
                    if (!FS)            select <= 1'b1;
                    else                select <= 1'b0;
                    state <= S5;
                end

                S3 : state <= S4;

                S4 : state <= S0;

                S5 : begin
                    if (select)         state <= S0;
                    else                state <= S3;
                end
            endcase
        end
    end

    always @(*) begin
        case (state)
            //               RYGL RYL
            S0 : lights = 7'b0010_100;
            S1 : lights = 7'b0100_100;
            S2 : lights = 7'b0001_100;
            S3 : lights = 7'b1000_001;
            S4 : lights = 7'b1000_010;
            S5 : lights = 7'b0100_100;
        endcase
    end
endmodule

lab9/TLC_tb_v2.v
`timescale 1ns/1ps

module TLC_tb;
    reg HS;
    reg FS;
    reg clk;
    reg rstn;

    wire HR;
    wire HY;
    wire HL;
    wire HG;
    wire FR;
    wire FY;
    wire FL;

    TLC TLC(
        .HS(HS),
        .FS(FS),
        .FR(FR),
        .FY(FY),
        .FL(FL),
        .HR(HR),
        .HY(HY),
        .HL(HL), 
        .HG(HG),
        .clk(clk),
        .rstn(rstn)
    );

    initial forever
        #2.5 clk = ~clk;

    initial begin
        $dumpfile ("dumpfile.vcd");
        $dumpvars;
    end

    initial begin
        HS = 0;
        FS = 0;
        clk = 1;
        rstn = 1;
        
        // ** TODO ** //
        #3 rstn = 0;
        #4 HS = 1;
        #6 FS = 1;
        #4 HS = 1;
        #9 FS = 1;
        #17 FS = 1;
        #3 HS = 1;
        #10 HS = 1;
        #21 HS = 1;
        FS = 1;
        // ********** //
        #20 $finish;
    end

    always @(HR, HY, HG, HL, FR, FY, FL) begin
        $write ($time, " : ");
        if (HR) $write ("HR");
        if (HY) $write ("HY");
        if (HG) $write ("HG");
        if (HL) $write ("HL");
        if (FR) $write ("FR");
        if (FY) $write ("FY");
        if (FL) $write ("FL");

        $write ("\n");
    end

    always @(negedge HL) begin
        HS = 0;
    end

    always @(negedge FL) begin
        FS = 0;
    end
endmodule

lab9/dumpfile.vcd
$date
	Sat Nov 12 19:21:17 2022
$end
$version
	Icarus Verilog
$end
$timescale
	1ps
$end
$scope module TLC_tb $end
$var wire 1 ! HY $end
$var wire 1 " HR $end
$var wire 1 # HL $end
$var wire 1 $ HG $end
$var wire 1 % FY $end
$var wire 1 & FR $end
$var wire 1 ' FL $end
$var reg 1 ( FS $end
$var reg 1 ) HS $end
$var reg 1 * clk $end
$var reg 1 + rstn $end
$scope module TLC $end
$var wire 1 ( FS $end
$var wire 1 ) HS $end
$var wire 1 * clk $end
$var wire 1 + rstn $end
$var wire 1 ! HY $end
$var wire 1 " HR $end
$var wire 1 # HL $end
$var wire 1 $ HG $end
$var wire 1 % FY $end
$var wire 1 & FR $end
$var wire 1 ' FL $end
$var reg 7 , lights [6:0] $end
$var reg 1 - select $end
$var reg 3 . state [2:0] $end
$upscope $end
$upscope $end
$enddefinitions $end
#0
$dumpvars
b0 .
1-
b10100 ,
1+
1*
0)
0(
0'
1&
0%
1$
0#
0"
0!
$end
#2500
0*
#3000
0+
#5000
1*
#7000
1)
#7500
0*
#10000
1!
0$
b100100 ,
b1 .
0-
1*
#12500
0*
#13000
1(
#15000
0!
1#
b1100 ,
b10 .
1*
#17500
0*
#20000
0)
1!
0#
b100100 ,
b101 .
1*
#22500
0*
#25000
1"
0!
0&
1'
b1000001 ,
b11 .
1*
#27500
0*
#30000
0(
1%
0'
b1000010 ,
b100 .
1*
#32500
0*
#35000
0"
1$
1&
0%
b10100 ,
b0 .
1*
#37500
0*
#40000
1*
#42500
0*
#43000
1(
#45000
1!
0$
b100100 ,
b1 .
1-
1*
#46000
1)
#47500
0*
#50000
1"
0!
0&
1'
b1000001 ,
0-
b11 .
1*
#52500
0*
#55000
0(
1%
0'
b1000010 ,
b100 .
1*
#57500
0*
#60000
0"
1$
1&
0%
b10100 ,
b0 .
1*
#62500
0*
#65000
1!
0$
b100100 ,
b1 .
1*
#67500
0*
#70000
0!
1#
b1100 ,
b10 .
1*
#72500
0*
#75000
0)
1!
0#
b100100 ,
b101 .
1-
1*
#77000
1(
1)
#77500
0*
#80000
0!
1$
b10100 ,
b0 .
1*
#82500
0*
#85000
1!
0$
b100100 ,
b1 .
0-
1*
#87500
0*
#90000
0!
1#
b1100 ,
b10 .
1*
#92500
0*
#95000
0)
1!
0#
b100100 ,
b101 .
1*
